fastrouge/__init__.py
fastrouge-0.0.1.dist-info/LICENSE
fastrouge-0.0.1.dist-info/METADATA
fastrouge-0.0.1.dist-info/WHEEL
fastrouge-0.0.1.dist-info/top_level.txt
fastrouge-0.0.1.dist-info/RECORD
