Metadata-Version: 2.1
Name: fastrouge
Version: 0.0.1
Summary: A rouge tool written in Python
Home-page: https://github.com/fastnlp/fastSum
Author: FudanNLP
License: Apache License
Platform: UNKNOWN
Requires-Python: >=3.6
Requires-Dist: fastNLP (>=0.5.5)
